<?xml version="1.0" encoding="utf-8" ?>
<LanguageData>

  <Level>등급</Level>
  <ProgressToNextLevel>경험치</ProgressToNextLevel>
  <Passion>열정</Passion>
  <PassionNone>관심 없음 (학습 {0}x)</PassionNone>
  <PassionMinor>흥미 있음 (학습 {0}x)</PassionMinor>
  <PassionMajor>불타오름 (학습 {0}x)</PassionMajor>
  <EffectsAtLevel>등급 {0}에서 발휘하는 효과</EffectsAtLevel>
  <SkillMax>최대</SkillMax>



  <Skill0>할 수 없음</Skill0>
  <Skill1>문외한</Skill1>
  <Skill2>기초만 들어 봄</Skill2>
  <Skill3>기본적인 익숙함</Skill3>
  <Skill4>아마추어</Skill4>
  <Skill5>경험 많은 아마추어</Skill5>
  <Skill6>수습생</Skill6>
  <Skill7>경험 많은 수습생</Skill7>
  <Skill8>직업인</Skill8>
  <Skill9>경험 많은 직업인</Skill9>
  <Skill10>전문가</Skill10>
  <Skill11>고급 전문가</Skill11>
  <Skill12>초고급 전문가</Skill12>
  <Skill13>장인</Skill13>
  <Skill14>지역급 장인</Skill14>
  <Skill15>행성급 장인</Skill15>
  <Skill16>항성계급 장인</Skill16>
  <Skill17>존경받는 장인</Skill17>
  <Skill18>선구자</Skill18>
  <Skill19>전설</Skill19>
  <Skill20>신적 존재</Skill20>


  
  
  
</LanguageData>
