<?xml version="1.0" encoding="UTF-8"?>
<LanguageData>
  <Bossgroup.questContentRules.rulesStrings>
    <li>bossDefeatedLetterLabel->[escortees0_label] 패배함: [reward_label]</li>
    <li>bossDefeatedStudyChipLetterText->[defeated][study][manufacture]</li>
    <li>bossDefeatedLetterText->[defeated][manufacture]</li>
    <li>defeated->적대적인 [escortees0_label](이)가 쓰러지며 [reward_label](을)를 떨어트렸습니다!</li>
    <li>manufacture->\n\n이 칩은 더욱 발달된 메카노이드를 만들 때 사용할 수 있습니다.</li>
    <li>study->\n\n메카나이터를 선택하고 [reward_label](을)를 오른쪽 클릭해서 연구할 수 있습니다. [reward_label](을)를 연구하면 상위 기계공학 연구의 잠금을 해제할 수 있습니다.</li>
  </Bossgroup.questContentRules.rulesStrings>
  <Bossgroup.questDescriptionRules.rulesStrings>
    <li>questDescription->bossgroup</li>
  </Bossgroup.questDescriptionRules.rulesStrings>
  <Bossgroup.questNameRules.rulesStrings>
    <li>questName->bossgroup</li>
  </Bossgroup.questNameRules.rulesStrings>
</LanguageData>
