<?xml version="1.0" encoding="UTF-8"?>
<LanguageData>
  
  <!-- EN: [PAWN_nameDef] spent almost all of [PAWN_possessive] time indoors, away from other humans. To survive, [PAWN_pronoun] trained and sold messenger rats. -->
  <CynapseCustomAdulthood.description>{PAWN_nameDef}(은)는 대부분의 시간을 다른 사람과의 접촉 없이 실내에서 지냈습니다. {PAWN_pronoun}는 살아남기 위해서 파발쥐들을 훈련하고 팔았습니다.</CynapseCustomAdulthood.description>
  <!-- EN: hermit -->
  <CynapseCustomAdulthood.title>은둔자</CynapseCustomAdulthood.title>
  <!-- EN: hermit -->
  <CynapseCustomAdulthood.titleShort>은둔자</CynapseCustomAdulthood.titleShort>
  
  <!-- EN: [PAWN_nameDef] spent most of [PAWN_possessive] time disassembling and reassembling electronic devices in order to figure out how they function. [PAWN_nameDef] became so preoccupied with [PAWN_possessive] tinkering that [PAWN_pronoun] forgot to develop social relationships with other humans. -->
  <CynapseCustomChildhood.description>{PAWN_nameDef}(은)는 대부분의 시간을 전자기기의 분해와 재조립으로 보내며 작동 방식을 탐구했습니다. 이 일에 너무나 몰두한 나머지, 다른 사람들과는 사회적 관계를 맺을 수 없었습니다.</CynapseCustomChildhood.description>
  <!-- EN: tinkerer -->
  <CynapseCustomChildhood.title>땜장이</CynapseCustomChildhood.title>
  <!-- EN: tinkerer -->
  <CynapseCustomChildhood.titleShort>땜장이</CynapseCustomChildhood.titleShort>
  
  <!-- EN: [PAWN_nameDef] spent all [PAWN_possessive] time running tabletop role-playing games as a way to connect socially with others. The game changed every year, and other players always loved [PAWN_possessive] worldbuilding and stories. -->
  <FeyCustomAdulthood.description>[PAWN_nameDef](은)는 대부분의 시간을 TRPG속 게임마스터를 하며 보냈습니다. 게임은 매번 바뀌었고 다른 사람들은 항상 [PAWN_pronoun](이)가 만든 세계와 이야기를 좋아했습니다.</FeyCustomAdulthood.description>
  <!-- EN: game master -->
  <FeyCustomAdulthood.title>게임 마스터</FeyCustomAdulthood.title>
  <!-- EN: game master -->
  <FeyCustomAdulthood.titleShort>게임 마스터</FeyCustomAdulthood.titleShort>
  
  <!-- EN: Growing up sheltered in an urbworld archology, [PAWN_nameDef] distracted [PAWN_objective]self by playing wargames and painting miniatures. While [PAWN_pronoun] was never very good at the game itself, it helped to connect [PAWN_objective] with others. -->
  <FeyCustomChildhood.description>초월도시계 수용소에서 자란 [PAWN_nameDef](은)는 미니어처를 도색하고 전쟁게임을 하며 시간을 보냈습니다. [PAWN_pronoun](이)가 게임 자체를 잘하진 못했지만, 다른 사람들과 사교를 맺는데는 도움이 되었습니다.</FeyCustomChildhood.description>
  <!-- EN: wargame fanatic -->
  <FeyCustomChildhood.title>전쟁 게임 폐인</FeyCustomChildhood.title>
  <!-- EN: wargame fanatic -->
  <FeyCustomChildhood.titleShort>전쟁 게임 폐인</FeyCustomChildhood.titleShort>
  
  <!-- EN: [PAWN_nameDef] was a hobbyist game developer who lived in an endless cycle of unfinished projects and lofty ideas. -->
  <JoeCustomAdulthood.description>[PAWN_nameDef](은)는 끝없는 프로젝트와 샘솟는 아이디어의 순환 속에 갇힌 게임 개발자였습니다.</JoeCustomAdulthood.description>
  <!-- EN: game developer -->
  <JoeCustomAdulthood.title>게임 개발자</JoeCustomAdulthood.title>
  <!-- EN: game dev -->
  <JoeCustomAdulthood.titleShort>게임 개발자</JoeCustomAdulthood.titleShort>
  
  <!-- EN: [PAWN_nameDef] was born into a family of musicians. When hard times came, [PAWN_pronoun] was forced to play the drum in a traveling band. -->
  <JoeCustomChildhood.description>[PAWN_nameDef](은)는 음악가 집안에서 태어났습니다. 어려웠던 시절, [PAWN_pronoun](은)는 이곳 저곳을 떠돌며 드럼을 연주해야만 했습니다.</JoeCustomChildhood.description>
  <!-- EN: drummer -->
  <JoeCustomChildhood.title>드러머</JoeCustomChildhood.title>
  <!-- EN: drummer -->
  <JoeCustomChildhood.titleShort>드러머</JoeCustomChildhood.titleShort>
  
  <!-- EN: [PAWN_nameDef] worked on a peaceful glitterworld developing hyper-realistic war crime simulation software. -->
  <LiamCustomAdulthood.description>[PAWN_nameDef](은)는 평화로운 번화계에서 초현실적인 전쟁 범죄 시뮬레이션 소프트웨어를 개발했습니다.</LiamCustomAdulthood.description>
  <!-- EN: simulation developer -->
  <LiamCustomAdulthood.title>시뮬레이션 개발자</LiamCustomAdulthood.title>
  <!-- EN: sim dev -->
  <LiamCustomAdulthood.titleShort>시뮬레이션 개발자</LiamCustomAdulthood.titleShort>
  
  <!-- EN: Born and raised on a glitterworld, [PAWN_nameDef] was obsessed with simulation software. [PAWN_pronoun] spent far too much time plugged in. -->
  <LiamCustomChildhood.description>번화계에서 태어나고 자란 [PAWN_nameDef](은)는 가상 시뮬레이션에 심취했습니다. [PAWN_pronoun](은)는 너무 오래도록 접속하는데 시간을 보냈습니다.</LiamCustomChildhood.description>
  <!-- EN: sim addict -->
  <LiamCustomChildhood.title>시뮬레이션 중독자</LiamCustomChildhood.title>
  <!-- EN: sim addict -->
  <LiamCustomChildhood.titleShort>시뮬레이션 중독자</LiamCustomChildhood.titleShort>
  
  <!-- EN: After being laid off by an interplanetary megacorp, [PAWN_nameDef] spent several years disillusioned and fighting alcohol addiction.\n\n[PAWN_pronoun] ended up busking aboard a space freighter, playing a beaten-up guitar and entertaining the crew with blues and folk songs from the distant past. -->
  <MateCustomAdulthood.description>거대 재벌 기업에서 해고당한 후, {PAWN_nameDef}(은)는 수 년간 좌절한 채 알코올 중독과 싸우며 보냈습니다.\n\n마침내 {PAWN_nameDef}(은)는 우주 화물선에 탑승해 망가진 기타로 오래된 블루스와 민요를 부르며 선원들을 즐겁게 했습니다.</MateCustomAdulthood.description>
  <!-- EN: busker -->
  <MateCustomAdulthood.title>노상공연가</MateCustomAdulthood.title>
  <!-- EN: busker -->
  <MateCustomAdulthood.titleShort>노상공연가</MateCustomAdulthood.titleShort>
  
  <!-- EN: [PAWN_nameDef] spent most of [PAWN_possessive] childhood dreaming of becoming a famous artist who could impress people with [PAWN_possessive] creations. -->
  <MateCustomChildhood.description>{PAWN_nameDef}(은)는 유명한 아티스트가 되는 꿈을 꾸며 대부분의 시간을 보냈습니다.</MateCustomChildhood.description>
  <!-- EN: curious kid -->
  <MateCustomChildhood.title>호기심 많은 아이</MateCustomChildhood.title>
  <!-- EN: curious kid -->
  <MateCustomChildhood.titleShort>호기심 많은 아이</MateCustomChildhood.titleShort>
  
  <!-- EN: [PAWN_nameDef] carved living spaces and mined minerals from the sides of hills and mountains. [PAWN_pronoun] learned to feel at home picking through rock and shoring up cave walls. -->
  <NathanCustomAdulthood.description>{PAWN_nameDef}(은)는 산과 언덕의 허리에서 살 공간을 파내는 일을 했습니다. {PAWN_pronoun}는 바위를 파고 동굴 벽을 강화하는 일을 하며 마치 집처럼 편안함을 느낍니다.</NathanCustomAdulthood.description>
  <!-- EN: digger -->
  <NathanCustomAdulthood.title>땅굴꾼</NathanCustomAdulthood.title>
  <!-- EN: digger -->
  <NathanCustomAdulthood.titleShort>땅굴꾼</NathanCustomAdulthood.titleShort>
  
  <!-- EN: [PAWN_nameDef] grew up in a large and intricate cave complex that extended deep into a mountainside. [PAWN_pronoun] helped the adults maintain and improve the deep caves. -->
  <NathanCustomChildhood.description>{PAWN_nameDef}(은)는 산 깊숙이 뻗어있는 크고 복잡한 동굴에서 자랐습니다. {PAWN_pronoun}는 어른들이 깊은 동굴을 보수하고 개선하는 걸 도왔습니다.</NathanCustomChildhood.description>
  <!-- EN: cave child -->
  <NathanCustomChildhood.title>동굴의 아이</NathanCustomChildhood.title>
  <!-- EN: cave child -->
  <NathanCustomChildhood.titleShort>동굴의 아이</NathanCustomChildhood.titleShort>
  
  <!-- EN: [PAWN_nameDef] designed combat modifications for frontline soldiers.\n\nOne night, in a nightmare, [PAWN_nameDef] was confronted by all the men and women killed by [PAWN_possessive] work. [PAWN_pronoun] decided to travel to the rimworlds and use [PAWN_possessive] skills for good. -->
  <OskarCustomAdulthood.description>{PAWN_nameDef}(은)는 최전선 군인을 위한 전투 모드를 설계했습니다.\n\n어느 날 밤 악몽 속에서 {PAWN_nameDef}의 직무로 죽은 모든 남녀를 마주하게 되었고, {PAWN_pronoun}는 변경계로 여행을 떠나 자신의 기술을 좋은 일에 사용하기로 마음먹었습니다.</OskarCustomAdulthood.description>
  <!-- EN: mod designer -->
  <OskarCustomAdulthood.title>모드 설계자</OskarCustomAdulthood.title>
  <!-- EN: modder -->
  <OskarCustomAdulthood.titleShort>모더</OskarCustomAdulthood.titleShort>
  
  <!-- EN: [PAWN_nameDef] was born on the dark edge of a tidally-locked urbworld. After an argument, [PAWN_possessive] father sold [PAWN_objective] to a local district lord as a slave artist.\n\nForced to create art or be punished, [PAWN_pronoun] withdrew and became unable to form relations with others. -->
  <OskarCustomChildhood.description>{PAWN_nameDef}(은)는 조석 고정된 도시계 행성의 어둠 끝자락에서 태어났습니다. {PAWN_possessive}의 아버지와 싸운 후, {PAWN_nameDef}(은)는 그 지역의 지배자에게 노예 예술가로 팔려갔습니다.\n\n예술품을 만들거나 처벌을 받는 선택지 사이에서 고통받으며, {PAWN_nameDef}(은)는 다른 사람과 관계를 맺을 수 없게 됐습니다.</OskarCustomChildhood.description>
  <!-- EN: art slave -->
  <OskarCustomChildhood.title>예술 노예</OskarCustomChildhood.title>
  <!-- EN: artist -->
  <OskarCustomChildhood.titleShort>예술가</OskarCustomChildhood.titleShort>
  
  <!-- EN: [PAWN_nameDef] was an independent game developer.\n\nAfter an early success, [PAWN_possessive] career quickly degenerated into a circus of misguided ideas, deals gone wrong, and desperate, failed PR stunts. -->
  <TynanCustomAdulthood.description>{PAWN_nameDef}(은)는 인디게임 개발자였습니다.\n\n이른 성공 후, {PAWN_possessive} 경력은 잘못된 아이디어, 지켜지지 않은 약속, 절박했지만 실패한 광고로 완전히 추락했습니다.</TynanCustomAdulthood.description>
  <!-- EN: game developer -->
  <TynanCustomAdulthood.title>게임 개발자</TynanCustomAdulthood.title>
  <!-- EN: game dev -->
  <TynanCustomAdulthood.titleShort>게임 개발자</TynanCustomAdulthood.titleShort>
  
  <!-- EN: [PAWN_nameDef] spent his childhood selling knockoff cigarettes to 15-year-olds. The cigarettes were often full of grass clippings. -->
  <TynanCustomChildhood.description>{PAWN_nameDef}(은)는 동급생들에게 싸구려 사제담배를 팔며 유년기를 보냈습니다. 담배에는 보통 잡초가 많이 섞여있었습니다.</TynanCustomChildhood.description>
  <!-- EN: punk -->
  <TynanCustomChildhood.title>불량 청소년</TynanCustomChildhood.title>
  <!-- EN: punk -->
  <TynanCustomChildhood.titleShort>불량 청소년</TynanCustomChildhood.titleShort>
  
  <!-- EN: [PAWN_nameDef] designed elaborate entertainment mazes for the glitterworld elite. Even now, [PAWN_pronoun] thinks of little else. -->
  <WillCustomAdulthood.description>{PAWN_nameDef}(은)는 번화계 고위층을 위한 정교한 오락용 미로를 설계했습니다. 심지어 지금도 미로 외에 다른 생각은 거의 하지 않습니다.</WillCustomAdulthood.description>
  <!-- EN: labyrinth maker -->
  <WillCustomAdulthood.title>미궁 제작자</WillCustomAdulthood.title>
  <!-- EN: labyrinth maker -->
  <WillCustomAdulthood.titleShort>미궁 제작자</WillCustomAdulthood.titleShort>
  
  <!-- EN: [PAWN_nameDef] grew up in a research camp on a deadworld. [PAWN_possessive] parents were astrobiologists studying mysterious labyrinthine formations beneath the planet's crust. [PAWN_pronoun] spent most of his time wandering those tunnels, wondering what otherworldly entity could have created them. -->
  <WillCustomChildhood.description>{PAWN_nameDef}(은)는 죽음계 연구기지에서 자랐습니다. {PAWN_possessive}의 부모는 그 행성의 지각 밑에 형성된 신비한 미궁 구조를 연구하는 천체생물학자였습니다. {PAWN_nameDef}(은)는 대부분의 시간을 땅굴 속에서 지내며, 어떤 기이한 생물체들이 그곳에서 탄생했을까 상상하곤 했습니다.</WillCustomChildhood.description>
  <!-- EN: maze child -->
  <WillCustomChildhood.title>미로의 아이</WillCustomChildhood.title>
  <!-- EN: maze child -->
  <WillCustomChildhood.titleShort>미로의 아이</WillCustomChildhood.titleShort>
  
</LanguageData>