<?xml version="1.0" encoding="utf-8" ?>
<!--suppress ALL -->
<LanguageData>

	<Misc.label>기타</Misc.label>
	<Misc.injury.oldLabel>흉터</Misc.injury.oldLabel>
	<Misc.injury.destroyedLabel>파괴됨</Misc.injury.destroyedLabel>
	<Misc.injury.treatedWellLabel>붕대 감음</Misc.injury.treatedWellLabel>
	<Misc.injury.treatedLabel>형편없이 붕대 감음</Misc.injury.treatedLabel>
	<Misc.injury.innerTreatedWellLabel>봉합됨</Misc.injury.innerTreatedWellLabel>
	<Misc.injury.innerTreatedLabel>형편없이 봉합됨</Misc.injury.innerTreatedLabel>
	<Misc.injury.solidTreatedWellLabel>접합됨</Misc.injury.solidTreatedWellLabel>
	<Misc.injury.solidTreatedLabel>형편없이 접합됨</Misc.injury.solidTreatedLabel>
	
	<Burn.label>화상</Burn.label>
	<Burn.injury.oldLabel>화상 흉터</Burn.injury.oldLabel>
	<Burn.injury.destroyedLabel>불에 타버림</Burn.injury.destroyedLabel>
	<Burn.injury.destroyedOutLabel>불에 타버림</Burn.injury.destroyedOutLabel>
	<Burn.injury.treatedWellLabel>붕대 감음</Burn.injury.treatedWellLabel>
	<Burn.injury.treatedLabel>형편없이 붕대 감음</Burn.injury.treatedLabel>
	<Burn.injury.innerTreatedWellLabel>봉합됨</Burn.injury.innerTreatedWellLabel>
	<Burn.injury.innerTreatedLabel>형편없이 봉합됨</Burn.injury.innerTreatedLabel>
	<Burn.injury.solidTreatedWellLabel>접합됨</Burn.injury.solidTreatedWellLabel>
	<Burn.injury.solidTreatedLabel>형편없이 접합됨</Burn.injury.solidTreatedLabel>
	
	<Crush.label>으스러짐</Crush.label>
	<Crush.injury.oldLabel>흉터</Crush.injury.oldLabel>
	<Crush.injury.destroyedLabel>으스러짐</Crush.injury.destroyedLabel>
	<Crush.injury.treatedWellLabel>붕대 감음</Crush.injury.treatedWellLabel>
	<Crush.injury.treatedLabel>형편없이 붕대 감음</Crush.injury.treatedLabel>
	<Crush.injury.innerTreatedWellLabel>봉합됨</Crush.injury.innerTreatedWellLabel>
	<Crush.injury.innerTreatedLabel>형편없이 봉합됨</Crush.injury.innerTreatedLabel>
	<Crush.injury.solidTreatedWellLabel>접합됨</Crush.injury.solidTreatedWellLabel>
	<Crush.injury.solidTreatedLabel>형편없이 접합됨</Crush.injury.solidTreatedLabel>
	
	<Crack.label>골절</Crack.label>
	<Crack.injury.oldLabel>흉터</Crack.injury.oldLabel>
	<Crack.injury.destroyedLabel>부서짐</Crack.injury.destroyedLabel>
	<Crack.injury.treatedWellLabel>치유</Crack.injury.treatedWellLabel>
	<Crack.injury.treatedLabel>형편없이 치유</Crack.injury.treatedLabel>
	<Crack.injury.innerTreatedWellLabel>치유</Crack.injury.innerTreatedWellLabel>
	<Crack.injury.innerTreatedLabel>형편없이 치유</Crack.injury.innerTreatedLabel>
	<Crack.injury.solidTreatedWellLabel>접합됨</Crack.injury.solidTreatedWellLabel>
	<Crack.injury.solidTreatedLabel>형편없이 접합됨</Crack.injury.solidTreatedLabel>
	
	<Cut.label>베임</Cut.label>
	<Cut.injury.oldLabel>베인 흉터</Cut.injury.oldLabel>
	<Cut.injury.destroyedLabel>끊어짐</Cut.injury.destroyedLabel>
	<Cut.injury.destroyedOutLabel>잘림</Cut.injury.destroyedOutLabel>
	<Cut.injury.treatedWellLabel>붕대 감음</Cut.injury.treatedWellLabel>
	<Cut.injury.treatedLabel>형편없이 붕대 감음</Cut.injury.treatedLabel>
	<Cut.injury.innerTreatedWellLabel>봉합됨</Cut.injury.innerTreatedWellLabel>
	<Cut.injury.innerTreatedLabel>형편없이 봉합됨</Cut.injury.innerTreatedLabel>
	<Cut.injury.solidTreatedWellLabel>접합됨</Cut.injury.solidTreatedWellLabel>
	<Cut.injury.solidTreatedLabel>형편없이 접합됨</Cut.injury.solidTreatedLabel>
	
	<SurgicalCut.label>외과적 절단</SurgicalCut.label>
	<SurgicalCut.injury.oldLabel>베인 흉터</SurgicalCut.injury.oldLabel>
	<SurgicalCut.injury.treatedWellLabel>붕대 감음</SurgicalCut.injury.treatedWellLabel>
	<SurgicalCut.injury.treatedLabel>형편없이 붕대 감음</SurgicalCut.injury.treatedLabel>
	<SurgicalCut.injury.innerTreatedWellLabel>봉합됨</SurgicalCut.injury.innerTreatedWellLabel>
	<SurgicalCut.injury.innerTreatedLabel>형편없이 봉합됨</SurgicalCut.injury.innerTreatedLabel>
	<SurgicalCut.injury.solidTreatedWellLabel>접합됨</SurgicalCut.injury.solidTreatedWellLabel>
	<SurgicalCut.injury.solidTreatedLabel>형편없이 접합됨</SurgicalCut.injury.solidTreatedLabel>
	
	<Scratch.label>긁힘</Scratch.label>
	<Scratch.injury.oldLabel>긁힌 상처</Scratch.injury.oldLabel>
	<Scratch.injury.destroyedLabel>찢어짐</Scratch.injury.destroyedLabel>
	<Scratch.injury.destroyedOutLabel>찢겨나감</Scratch.injury.destroyedOutLabel>
	<Scratch.injury.treatedWellLabel>붕대 감음</Scratch.injury.treatedWellLabel>
	<Scratch.injury.treatedLabel>형편없이 붕대 감음</Scratch.injury.treatedLabel>
	<Scratch.injury.innerTreatedWellLabel>봉합됨</Scratch.injury.innerTreatedWellLabel>
	<Scratch.injury.innerTreatedLabel>형편없이 봉합됨</Scratch.injury.innerTreatedLabel>
	<Scratch.injury.solidTreatedWellLabel>접합됨</Scratch.injury.solidTreatedWellLabel>
	<Scratch.injury.solidTreatedLabel>형편없이 접합됨</Scratch.injury.solidTreatedLabel>
	
	<Bite.label>물림</Bite.label>
	<Bite.injury.oldLabel>물린 상처</Bite.injury.oldLabel>
	<Bite.injury.destroyedLabel>물어뜯김</Bite.injury.destroyedLabel>
	<Bite.injury.destroyedOutLabel>물어뜯김</Bite.injury.destroyedOutLabel>
	<Bite.injury.treatedWellLabel>붕대 감음</Bite.injury.treatedWellLabel>
	<Bite.injury.treatedLabel>형편없이 붕대 감음</Bite.injury.treatedLabel>
	<Bite.injury.innerTreatedWellLabel>봉합됨</Bite.injury.innerTreatedWellLabel>
	<Bite.injury.innerTreatedLabel>형편없이 봉합됨</Bite.injury.innerTreatedLabel>
	<Bite.injury.solidTreatedWellLabel>접합됨</Bite.injury.solidTreatedWellLabel>
	<Bite.injury.solidTreatedLabel>형편없이 접합됨</Bite.injury.solidTreatedLabel>
	
	<Stab.label>찔림</Stab.label>
	<Stab.injury.oldLabel>찔린 상처</Stab.injury.oldLabel>
	<Stab.injury.destroyedLabel>끊어짐</Stab.injury.destroyedLabel>
	<Stab.injury.destroyedOutLabel>잘려짐</Stab.injury.destroyedOutLabel>
	<Stab.injury.treatedWellLabel>붕대 감음</Stab.injury.treatedWellLabel>
	<Stab.injury.treatedLabel>형편없이 붕대 감음</Stab.injury.treatedLabel>
	<Stab.injury.innerTreatedWellLabel>봉합됨</Stab.injury.innerTreatedWellLabel>
	<Stab.injury.innerTreatedLabel>형편없이 봉합됨</Stab.injury.innerTreatedLabel>
	<Stab.injury.solidTreatedWellLabel>접합됨</Stab.injury.solidTreatedWellLabel>
	<Stab.injury.solidTreatedLabel>형편없이 접합됨</Stab.injury.solidTreatedLabel>
	
	<Gunshot.label>총상</Gunshot.label>
	<Gunshot.injury.oldLabel>오래된 총상</Gunshot.injury.oldLabel>
	<Gunshot.injury.destroyedLabel>파괴됨</Gunshot.injury.destroyedLabel>
	<Gunshot.injury.destroyedOutLabel>파괴됨</Gunshot.injury.destroyedOutLabel>
	<Gunshot.injury.treatedWellLabel>붕대 감음</Gunshot.injury.treatedWellLabel>
	<Gunshot.injury.treatedLabel>형편없이 붕대 감음</Gunshot.injury.treatedLabel>
	<Gunshot.injury.innerTreatedWellLabel>봉합됨</Gunshot.injury.innerTreatedWellLabel>
	<Gunshot.injury.innerTreatedLabel>형편없이 봉합됨</Gunshot.injury.innerTreatedLabel>
	<Gunshot.injury.solidTreatedWellLabel>접합됨</Gunshot.injury.solidTreatedWellLabel>
	<Gunshot.injury.solidTreatedLabel>형편없이 접합됨</Gunshot.injury.solidTreatedLabel>
	
	<Shredded.label>조각남</Shredded.label>
	<Shredded.injury.oldLabel>상처</Shredded.injury.oldLabel>
	<Shredded.injury.destroyedLabel>찢어짐</Shredded.injury.destroyedLabel>
	<Shredded.injury.destroyedOutLabel>벗겨짐</Shredded.injury.destroyedOutLabel>
	<Shredded.injury.treatedWellLabel>붕대 감음</Shredded.injury.treatedWellLabel>
	<Shredded.injury.treatedLabel>형편없이 붕대 감음</Shredded.injury.treatedLabel>
	<Shredded.injury.innerTreatedWellLabel>봉합됨</Shredded.injury.innerTreatedWellLabel>
	<Shredded.injury.innerTreatedLabel>형편없이 봉합됨</Shredded.injury.innerTreatedLabel>
	<Shredded.injury.solidTreatedWellLabel>접합됨</Shredded.injury.solidTreatedWellLabel>
	<Shredded.injury.solidTreatedLabel>형편없이 접합됨</Shredded.injury.solidTreatedLabel>
	
	<Bruise.label>타박상</Bruise.label>
	<Bruise.injury.oldLabel>오래된 타박상</Bruise.injury.oldLabel>
	<Bruise.injury.destroyedLabel>파괴됨</Bruise.injury.destroyedLabel>
	<Bruise.injury.treatedWellLabel>붕대 감음</Bruise.injury.treatedWellLabel>
	<Bruise.injury.treatedLabel>형편없이 붕대 감음</Bruise.injury.treatedLabel>
	<Bruise.injury.innerTreatedWellLabel>봉합됨</Bruise.injury.innerTreatedWellLabel>
	<Bruise.injury.innerTreatedLabel>형편없이 봉합됨</Bruise.injury.innerTreatedLabel>
	<Bruise.injury.solidTreatedWellLabel>접합됨</Bruise.injury.solidTreatedWellLabel>
	<Bruise.injury.solidTreatedLabel>형편없이 접합됨</Bruise.injury.solidTreatedLabel>
	
	<Frostbite.label>동상</Frostbite.label>
	<Frostbite.injury.oldLabel>동상 흉터</Frostbite.injury.oldLabel>
	<Frostbite.injury.destroyedLabel>동상으로 잃음</Frostbite.injury.destroyedLabel>
	<Frostbite.injury.treatedWellLabel>붕대 감음</Frostbite.injury.treatedWellLabel>
	<Frostbite.injury.treatedLabel>형편없이 붕대 감음</Frostbite.injury.treatedLabel>
	<Frostbite.injury.innerTreatedWellLabel>봉합됨</Frostbite.injury.innerTreatedWellLabel>
	<Frostbite.injury.innerTreatedLabel>형편없이 봉합됨</Frostbite.injury.innerTreatedLabel>
	<Frostbite.injury.solidTreatedWellLabel>접합됨</Frostbite.injury.solidTreatedWellLabel>
	<Frostbite.injury.solidTreatedLabel>형편없이 접합됨</Frostbite.injury.solidTreatedLabel>

	<!-- Missing body part -->
	<MissingBodyPart.label>신체 누락</MissingBodyPart.label>
	
</LanguageData>
