<?xml version="1.0" encoding="UTF-8"?>
<LanguageData>
  
  <!-- EN: [PAWN_nameDef] was the child of a lord and a prostitute.\n\n[PAWN_possessive] father's line was secure and his holdings strong. Nobody ever came to [PAWN_nameDef] to endorse a bid for the title. [PAWN_pronoun] earned [PAWN_possessive] bread cleaning the brothel, but always felt [PAWN_pronoun] deserved much more. -->
  <RoyalBastard64.baseDesc>{PAWN_nameDef}(은)는 왕과 매춘부 사이의 아이입니다.\n\n{PAWN_possessive} 부계 혈통은 확실했으며 권력은 강력했습니다. 하지만 아무도 {PAWN_nameDef}에게 직위를 얻기 위해 지지하지 않았었습니다. {PAWN_pronoun}는 끼니를 사창가를 청소하며 해결했었지만, 항상 {PAWN_pronoun}는 더 가치 있다고 생각했습니다.</RoyalBastard64.baseDesc>
  <!-- EN: royal bastard -->
  <RoyalBastard64.title>왕실 사생아</RoyalBastard64.title>
  <!-- EN: bastard -->
  <RoyalBastard64.titleShort>사생아</RoyalBastard64.titleShort>
  
  <!-- EN: [PAWN_nameDef] was the child of house servants, and was trained to carry on the family duty.\n\n[PAWN_pronoun] carried things and polished silverware, but was never allowed into the lords' part of the house. -->
  <ServingBoy97.baseDesc>{PAWN_nameDef}(은)는 하인의 자녀였고, 가정 업무를 수행할 수 있도록 훈련받았었습니다.\n\n{PAWN_pronoun}는 물건과 세련된 식기류를 운반했지만, 결코 가문의 일원으로 인정받지는 못했습니다.</ServingBoy97.baseDesc>
  <!-- EN: serving boy -->
  <ServingBoy97.title>심부름꾼</ServingBoy97.title>
  <!-- EN: serving girl -->
  <ServingBoy97.titleFemale>심부름꾼</ServingBoy97.titleFemale>
  <!-- EN: house boy -->
  <ServingBoy97.titleShort>심부름꾼</ServingBoy97.titleShort>
  <!-- EN: house girl -->
  <ServingBoy97.titleShortFemale>심부름꾼</ServingBoy97.titleShortFemale>
  
  <!-- EN: [PAWN_nameDef] was born nine months after [PAWN_possessive] mother's town was conquered by enemy soldiers. The child of violence with no acknowledged father, [PAWN_nameDef] grew up at the bottom of the social pyramid.\n\n[PAWN_possessive] mother instilled her bitterness towards men and war into [PAWN_nameDef]. [PAWN_possessive] pet rabbit offered more warmth than any human in [PAWN_possessive] life. -->
  <WarBastard60.baseDesc>{PAWN_nameDef}(은)는 {PAWN_possessive} 어머니의 마을이, 적군에 의해 점령되고, 9개월 후에 태어났습니다. 아버지가 없는 자녀인 {PAWN_nameDef}(은)는 사회 구조 맨 아래에서 자랐습니다.\n\n{PAWN_possessive} 어머니는 남자와 전쟁에 대한 괴로움으로 {PAWN_nameDef}(와)과 마찰을 빚었고, {PAWN_possessive} 애완동물 토끼는 {PAWN_possessive} 생활에서 인간보다 더 따뜻함을 주었습니다.</WarBastard60.baseDesc>
  <!-- EN: war bastard -->
  <WarBastard60.title>전쟁 사생아</WarBastard60.title>
  <!-- EN: bastard -->
  <WarBastard60.titleShort>사생아</WarBastard60.titleShort>
  
</LanguageData>