<?xml version="1.0" encoding="UTF-8"?>
<LanguageData>
  
  <!-- EN:
    <li>r_name->The [spaceAdj] Salvagers</li>
    <li>r_name->The [spaceAdj] Scavengers</li>
    <li>r_name->[spaceAdj] [AnimalBadass]s</li>
    <li>r_name->The [spaceAdj] [AnimalBadass]s</li>
    <li>r_name->The [spaceAdj] [Enemy]s</li>
    <li>r_name->The [spaceNoun] [Enemy]s</li>
    <li>r_name->The [spaceNoun] [groupname]</li>
    <li>r_name->The [spaceAdj] [groupname]</li>
    <li>r_name->The [ColorBadass] [spaceNoun]</li>
    <li>r_name->The [AdjectiveBadass] [spaceNoun]</li>
    <li>r_name->The [ColorBadass] [spaceCollectiveNoun]</li>
    <li>r_name->The [AdjectiveBadass] [spaceCollectiveNoun]</li>
    <li>r_name->The [spaceNoun]s of [ConceptBadass]</li>
    <li>r_name(p=2)->[NamePerson]'s [spaceNoun]s</li>
    <li>r_name(p=2)->[NamePerson]'s [spaceCollectiveNoun]</li>
    <li>r_name(p=2)->[NamePerson]'s [spaceAdj] [spaceCollectiveNoun]</li>
    <li>spaceAdj->Orbital</li>
    <li>spaceAdj->Cosmic</li>
    <li>spaceAdj->Astral</li>
    <li>spaceAdj->Solar</li>
    <li>spaceAdj->Celestial</li>
    <li>spaceNoun->Star</li>
    <li>spaceNoun->Moon</li>
    <li>spaceNoun->Comet</li>
    <li>spaceNoun->Asteroid</li>
    <li>spaceNoun->Eclipse</li>
    <li>spaceCollectiveNoun->Armada</li>
    <li>spaceCollectiveNoun->Fleet</li>
    <li>spaceCollectiveNoun->Flotilla</li>
    <li>spaceCollectiveNoun->Fleet</li>
    <li>spaceCollectiveNoun->Corsairs</li>
    <li>spaceCollectiveNoun->Pirates</li>
    <li>spaceCollectiveNoun->Marauders</li>
    <li>spaceCollectiveNoun->Reapers</li>
  -->
  <NamerFactionSalvagers.rulePack.rulesStrings>
    <li>r_name->The [spaceAdj] 구조자들</li>
    <li>r_name->The [spaceAdj] 청소부들</li>
    <li>r_name->[spaceAdj] [AnimalBadass]들</li>
    <li>r_name->The [spaceAdj] [AnimalBadass]들</li>
    <li>r_name->The [spaceAdj] [Enemy]들</li>
    <li>r_name->The [spaceNoun] [Enemy]들</li>
    <li>r_name->The [spaceNoun] [groupname]</li>
    <li>r_name->The [spaceAdj] [groupname]</li>
    <li>r_name->The [ColorBadass] [spaceNoun]</li>
    <li>r_name->The [AdjectiveBadass] [spaceNoun]</li>
    <li>r_name->The [ColorBadass] [spaceCollectiveNoun]</li>
    <li>r_name->The [AdjectiveBadass] [spaceCollectiveNoun]</li>
    <li>r_name->The [spaceNoun]들 of [ConceptBadass]</li>
    <li>r_name(p=2)->[NamePerson]의 [spaceNoun]들</li>
    <li>r_name(p=2)->[NamePerson]의 [spaceCollectiveNoun]</li>
    <li>r_name(p=2)->[NamePerson]의 [spaceAdj] [spaceCollectiveNoun]</li>
    <li>spaceAdj->궤도</li>
    <li>spaceAdj->코스믹</li>
    <li>spaceAdj->천상</li>
    <li>spaceAdj->태양</li>
    <li>spaceAdj->천체</li>
    <li>spaceNoun->별</li>
    <li>spaceNoun->달</li>
    <li>spaceNoun->혜성</li>
    <li>spaceNoun->소행성</li>
    <li>spaceNoun->일식</li>
    <li>spaceCollectiveNoun->함대</li>
    <li>spaceCollectiveNoun->선단</li>
    <li>spaceCollectiveNoun->대집단</li>
    <li>spaceCollectiveNoun->플리트</li>
    <li>spaceCollectiveNoun->해적단</li>
    <li>spaceCollectiveNoun->마라더즈</li>
    <li>spaceCollectiveNoun->리퍼즈</li>
  </NamerFactionSalvagers.rulePack.rulesStrings>
  
  <!-- EN:
    <li>r_name->[tradeAdj] [tradeNoun]</li>
    <li>tradeAdj->merchant's</li>
    <li>tradeAdj->orbital</li>
    <li>tradeAdj->trade</li>
    <li>tradeAdj->spacer's</li>
    <li>tradeAdj->space</li>
    <li>tradeAdj->cosmic</li>
    <li>tradeAdj->skyflight</li>
    <li>tradeAdj->voidborn</li>
    <li>tradeAdj->exo</li>
    <li>tradeNoun->guild</li>
    <li>tradeNoun->consortium</li>
    <li>tradeNoun->syndicate</li>
    <li>tradeNoun->alliance</li>
    <li>tradeNoun->cartel</li>
    <li>tradeNoun->coalition</li>
    <li>tradeNoun->federation</li>
    <li>tradeNoun->conglomerate</li>
    <li>tradeNoun->corporation</li>
    <li>tradeNoun->company</li>
    <li>tradeNoun->network</li>
    <li>tradeNoun->exchange</li>
    <li>tradeNoun->bazaar</li>
    <li>tradeNoun->emporium</li>
    <li>tradeNoun->nexus</li>
  -->
  <NamerFactionTradersGuild.rulePack.rulesStrings>
    <li>r_name->[tradeAdj] [tradeNoun]</li>
    <li>tradeAdj->상인의</li>
    <li>tradeAdj->궤도</li>
    <li>tradeAdj->교역</li>
    <li>tradeAdj->우주인</li>
    <li>tradeAdj->우주</li>
    <li>tradeAdj->코스믹</li>
    <li>tradeAdj->하늘비행</li>
    <li>tradeAdj->공허 출신</li>
    <li>tradeAdj->엑소</li>
    <li>tradeNoun->길드</li>
    <li>tradeNoun->컨소시엄</li>
    <li>tradeNoun->신디케이트</li>
    <li>tradeNoun->동맹</li>
    <li>tradeNoun->카르텔</li>
    <li>tradeNoun->연합</li>
    <li>tradeNoun->연방</li>
    <li>tradeNoun->콩글로메리트</li>
    <li>tradeNoun->코퍼레이션</li>
    <li>tradeNoun->컴퍼니</li>
    <li>tradeNoun->네트워크</li>
    <li>tradeNoun->거래소</li>
    <li>tradeNoun->시장</li>
    <li>tradeNoun->상점</li>
    <li>tradeNoun->넥서스</li>
  </NamerFactionTradersGuild.rulePack.rulesStrings>
  
  <!-- EN:
    <li>r_name->[platAdj] [platform]</li>
    <li>platAdj->starlight</li>
    <li>platAdj->sunshine</li>
    <li>platAdj->nebula</li>
    <li>platAdj->stardust</li>
    <li>platAdj->orion</li>
    <li>platAdj->horizon</li>
    <li>platAdj->galaxy</li>
    <li>platAdj->cosmos</li>
    <li>platAdj->void</li>
    <li>platAdj->asteroid</li>
    <li>platAdj->comet</li>
    <li>platAdj->eclipse</li>
    <li>platAdj->quasar</li>
    <li>platAdj->pulsar</li>
    <li>platAdj->meteor</li>
    <li>platAdj->zenith</li>
    <li>platAdj->lunar</li>
    <li>platAdj->solar</li>
    <li>platAdj->celestial</li>
    <li>platAdj->moonbeam</li>
    <li>platAdj->sunburst</li>
    <li>platAdj->starfield</li>
    <li>platAdj->cosmic</li>
    <li>platAdj->astral</li>
    <li>platAdj->aurora</li>
    <li>platAdj->luminary</li>
    <li>platAdj->corona</li>
    <li>platform->platform</li>
    <li>platform->station</li>
    <li>platform->hub</li>
    <li>platform->station</li>
    <li>platform->base</li>
    <li>platform->dock</li>
    <li>platform->ring</li>
  -->
  <NamerSettlementTradersGuild.rulePack.rulesStrings>
    <li>r_name->[platAdj] [platform]</li>
    <li>platAdj->별빛</li>
    <li>platAdj->햇살</li>
    <li>platAdj->성운</li>
    <li>platAdj->별가루</li>
    <li>platAdj->오리온</li>
    <li>platAdj->지평선</li>
    <li>platAdj->은하</li>
    <li>platAdj->코스모스</li>
    <li>platAdj->공허</li>
    <li>platAdj->소행성</li>
    <li>platAdj->혜성</li>
    <li>platAdj->일식</li>
    <li>platAdj->퀘이사</li>
    <li>platAdj->펄서</li>
    <li>platAdj->유성</li>
    <li>platAdj->정점</li>
    <li>platAdj->달빛</li>
    <li>platAdj->태양</li>
    <li>platAdj->천체</li>
    <li>platAdj->문빔</li>
    <li>platAdj->썬버스트</li>
    <li>platAdj->별밭</li>
    <li>platAdj->코스믹</li>
    <li>platAdj->천상</li>
    <li>platAdj->오로라</li>
    <li>platAdj->루미너리</li>
    <li>platAdj->코로나</li>
    <li>platform->플랫폼</li>
    <li>platform->정거장</li>
    <li>platform->허브</li>
    <li>platform->스테이션</li>
    <li>platform->기지</li>
    <li>platform->독</li>
    <li>platform->반지</li>
  </NamerSettlementTradersGuild.rulePack.rulesStrings>
  
</LanguageData>