<?xml version="1.0" encoding="utf-8" ?>
<LanguageData>

	<Research.pawnLabel>Researcher</Research.pawnLabel>
	<Research.gerundLabel>연구</Research.gerundLabel>
	<Research.verb>Research at</Research.verb>
	<Research.tooltipDesc>연구 과제를 등록한 경우 연구를 실행합니다.</Research.tooltipDesc>
	
	<Cleaning.pawnLabel>Cleaner</Cleaning.pawnLabel>
	<Cleaning.gerundLabel>청소</Cleaning.gerundLabel>
	<Cleaning.verb>Clean</Cleaning.verb>
	<Cleaning.tooltipDesc>홈 지역으로 설정된 지역 내부를 청소하여 주민들의 불쾌감을 줄입니다.. (핏자국,먼지 등을 제거합니다)</Cleaning.tooltipDesc>
	
	<Hauling.pawnLabel>Hauler</Hauling.pawnLabel>
	<Hauling.gerundLabel>운반</Hauling.gerundLabel>
	<Hauling.verb>Haul</Hauling.verb>
	<Hauling.tooltipDesc>운반 명령을 수행합니다.</Hauling.tooltipDesc>
	
	<Art.pawnLabel>Artist</Art.pawnLabel>
	<Art.gerundLabel>예술</Art.gerundLabel>
	<Art.verb>Do art at</Art.verb>
	<Art.tooltipDesc>예술가들은 아름다운 예술을 보여줍니다.</Art.tooltipDesc>
	
	<Crafting.pawnLabel>Crafter</Crafting.pawnLabel>
	<Crafting.gerundLabel>제작</Crafting.gerundLabel>
	<Crafting.verb>Craft at</Crafting.verb>
	<Crafting.tooltipDesc>장인들은 원재료를 가공하여 새로운 것을 만들어 냅니다.</Crafting.tooltipDesc>
	
	<PlantCutting.pawnLabel>Plant cutter</PlantCutting.pawnLabel>
	<PlantCutting.gerundLabel>수확</PlantCutting.gerundLabel>
	<PlantCutting.verb>Cut</PlantCutting.verb>
	<PlantCutting.tooltipDesc>야생 식물을 제초하거나 수확합니다.</PlantCutting.tooltipDesc>
	
	<Growing.pawnLabel>Grower</Growing.pawnLabel>
	<Growing.gerundLabel>재배</Growing.gerundLabel>
	<Growing.verb>Grow</Growing.verb>
	<Growing.tooltipDesc>재배 구역이 지정되면 해당 장소로 이동하여 씨를 뿌리고 다 자란 작물을 수확합니다.</Growing.tooltipDesc>
	
	<Mining.pawnLabel>Miner</Mining.pawnLabel>
	<Mining.gerundLabel>채굴</Mining.gerundLabel>
	<Mining.verb>Mine</Mining.verb>
	<Mining.tooltipDesc>광물을 포함한 돌벽에 대해 채굴 작업을 실시합니다.</Mining.tooltipDesc>
	
	<Repair.pawnLabel>Repairer</Repair.pawnLabel>
	<Repair.gerundLabel>수리</Repair.gerundLabel>
	<Repair.verb>Repair</Repair.verb>
	<Repair.tooltipDesc>고장난 건물과 장비를 수리합니다.</Repair.tooltipDesc>
	
	<Construction.pawnLabel>Constructor</Construction.pawnLabel>
	<Construction.gerundLabel>건설</Construction.gerundLabel>
	<Construction.verb>Construct</Construction.verb>
	<Construction.tooltipDesc>건축가는 당신이 지정한 것을 건설합니다.</Construction.tooltipDesc>
	
	<Hunting.pawnLabel>Hunter</Hunting.pawnLabel>
	<Hunting.gerundLabel>사냥</Hunting.gerundLabel>
	<Hunting.verb>Hunt</Hunting.verb>
	<Hunting.tooltipDesc>사냥꾼은 사냥하기로 정한 동물을 죽입니다.</Hunting.tooltipDesc>
	
	<Cooking.pawnLabel>Cook</Cooking.pawnLabel>
	<Cooking.gerundLabel>요리</Cooking.gerundLabel>
	<Cooking.verb>Cook</Cooking.verb>
	<Cooking.tooltipDesc>요리사는 영양반죽 합성기를 채우고 식사를 준비합니다.</Cooking.tooltipDesc>
	
	<Warden.pawnLabel>Warden</Warden.pawnLabel>
	<Warden.gerundLabel>간수</Warden.gerundLabel>
	<Warden.verb>Handle</Warden.verb>
	<Warden.tooltipDesc>수감자를 고용하거나 말을 건네기도 하고 처형하기도 합니다. 그리고 수감자들에게 식사를 가져다 줍니다.</Warden.tooltipDesc>

	<Patient.pawnLabel>Patient</Patient.pawnLabel>
	<Patient.gerundLabel>환자</Patient.gerundLabel>
	<Patient.verb>Patient</Patient.verb>
	<Patient.tooltipDesc>치료를 받아야 하는 환자는 의료 침대로 이동합니다.</Patient.tooltipDesc>

	<Doctor.pawnLabel>Doctor</Doctor.pawnLabel>
	<Doctor.gerundLabel>치료</Doctor.gerundLabel>
	<Doctor.verb>Care for</Doctor.verb>
	<Doctor.tooltipDesc>주민들과 수감자들이 무기력 상태가 되면 치료를 하거나 음식을 먹여주기도 합니다.</Doctor.tooltipDesc>
	
	<Firefighter.pawnLabel>Firefighter</Firefighter.pawnLabel>
	<Firefighter.gerundLabel>소화</Firefighter.gerundLabel>
	<Firefighter.verb>Extinguish</Firefighter.verb>
	<Firefighter.tooltipDesc>정착지 내에서 불을 끕니다.</Firefighter.tooltipDesc>

</LanguageData>
