<?xml version="1.0" encoding="UTF-8"?>
<LanguageData>
  <ResurrectHeavyMech.label>대형 메카노이드 소생</ResurrectHeavyMech.label>
  <ResurrectHeavyMech.description>아군 대형 메카노이드를 재활성화하여 부활시킵니다. 메카노이드의 시체가 완전히 파괴되지 않는 이상 다시 되살릴 수 있습니다.</ResurrectHeavyMech.description>
  <ResurrectHeavyMech.jobString>메카노이드 재활성화 중.</ResurrectHeavyMech.jobString>
  
  <ResurrectLightMech.label>소형 메카노이드 소생</ResurrectLightMech.label>
  <ResurrectLightMech.description>아군 소형 메카노이드를 재활성화하여 부활시킵니다. 메카노이드의 시체가 완전히 파괴되지 않는 이상 다시 되살릴 수 있습니다.</ResurrectLightMech.description>
  <ResurrectLightMech.jobString>메카노이드 재활성화 중.</ResurrectLightMech.jobString>
  
  <ResurrectMediumMech.label>중형 메카노이드 소생</ResurrectMediumMech.label>
  <ResurrectMediumMech.description>아군 중형 메카노이드를 재활성화하여 부활시킵니다. 메카노이드의 시체가 완전히 파괴되지 않는 이상 다시 되살릴 수 있습니다.</ResurrectMediumMech.description>
  <ResurrectMediumMech.jobString>메카노이드 재활성화 중.</ResurrectMediumMech.jobString>
  
  <ResurrectUltraheavyMech.label>초대형 메카노이드 소생</ResurrectUltraheavyMech.label>
  <ResurrectUltraheavyMech.description>아군 초대형 메카노이드를 재활성화하여 부활시킵니다. 메카노이드의 시체가 완전히 파괴되지 않는 이상 다시 되살릴 수 있습니다.</ResurrectUltraheavyMech.description>
  <ResurrectUltraheavyMech.jobString>메카노이드 재활성화 중.</ResurrectUltraheavyMech.jobString>
</LanguageData>
