<?xml version="1.0" encoding="UTF-8"?>
<LanguageData>
  
  <!-- EN: alpha thrumbo -->
  <AlphaThrumbo.label>알파 스럼보</AlphaThrumbo.label>
  <!-- EN: alpha thrumbo calf -->
  <AlphaThrumbo.lifeStages.alpha_thrumbo_calf.label>알파 스럼보 새끼</AlphaThrumbo.lifeStages.alpha_thrumbo_calf.label>
  <!-- EN: alpha thrumbo calves -->
  <AlphaThrumbo.lifeStages.alpha_thrumbo_calf.labelPlural>알파 스럼보 새끼들</AlphaThrumbo.lifeStages.alpha_thrumbo_calf.labelPlural>
  
  <!-- EN: bog hound -->
  <BogHound.label>습지 사냥개</BogHound.label>
  <!-- EN: bog hound puppy -->
  <BogHound.lifeStages.bog_hound_puppy.label>습지 사냥개 강아지</BogHound.lifeStages.bog_hound_puppy.label>
  <!-- EN: bog hound puppies -->
  <BogHound.lifeStages.bog_hound_puppy.labelPlural>습지 사냥개 강아지들</BogHound.lifeStages.bog_hound_puppy.labelPlural>
  
  <!-- EN: scimitar cat -->
  <Cat_Scimitar.label>시미터캣</Cat_Scimitar.label>
  
  <!-- EN: mastodon -->
  <Mastodon.label>마스토돈</Mastodon.label>
  <!-- EN: mastodon calf -->
  <Mastodon.lifeStages.mastodon_calf.label>마스토돈 송아지</Mastodon.lifeStages.mastodon_calf.label>
  <!-- EN: mastodon calves -->
  <Mastodon.lifeStages.mastodon_calf.labelPlural>마스토돈 송아지들</Mastodon.lifeStages.mastodon_calf.labelPlural>
  
  <!-- EN: monitor lizard -->
  <MonitorLizard.label>왕도마뱀</MonitorLizard.label>
  
  <!-- EN: moose -->
  <Moose.label>무스</Moose.label>
  <!-- EN: moose -->
  <Moose.labelPlural>무스</Moose.labelPlural>
  <!-- EN: moose calf -->
  <Moose.lifeStages.moose_calf.label>무스 송아지</Moose.lifeStages.moose_calf.label>
  <!-- EN: moose calves -->
  <Moose.lifeStages.moose_calf.labelPlural>무스 송아지들</Moose.lifeStages.moose_calf.labelPlural>
  
  <!-- EN: porcupine -->
  <Porcupine.label>호저</Porcupine.label>
  
  <!-- EN: prairie dog -->
  <PrairieDog.label>프레리도그</PrairieDog.label>
  
  <!-- EN: great wolf -->
  <Wolf_Great.label>거대 늑대</Wolf_Great.label>
  <!-- EN: great wolves -->
  <Wolf_Great.labelPlural>거대 늑대들</Wolf_Great.labelPlural>
  <!-- EN: great wolf puppy -->
  <Wolf_Great.lifeStages.great_wolf_puppy.label>거대 늑대 강아지</Wolf_Great.lifeStages.great_wolf_puppy.label>
  <!-- EN: great wolf puppies -->
  <Wolf_Great.lifeStages.great_wolf_puppy.labelPlural>거대 늑대 강아지들</Wolf_Great.lifeStages.great_wolf_puppy.labelPlural>
  
  <!-- EN: wolverine -->
  <Wolverine.label>울버린</Wolverine.label>
  
</LanguageData>