<?xml version="1.0" encoding="UTF-8"?>
<LanguageData>
  
  <!-- EN: executed colonist -->
  <ExecutedColonist.label>정착민 처형</ExecutedColonist.label>
  
  <!-- EN: executed guest -->
  <ExecutedGuest.label>손님 처형</ExecutedGuest.label>
  
  <!-- EN: executed prisoner -->
  <ExecutedPrisoner.label>포로 처형</ExecutedPrisoner.label>
  
  <!-- EN: executed guilty prisoner -->
  <ExecutedPrisonerGuilty.label>죄수 처형</ExecutedPrisonerGuilty.label>
  
  <!-- EN: executed innocent prisoner -->
  <ExecutedPrisonerInnocent.label>무고한 죄수 처형</ExecutedPrisonerInnocent.label>
  
</LanguageData>